README.rst
css2json.py
setup.py
css2json.egg-info/PKG-INFO
css2json.egg-info/SOURCES.txt
css2json.egg-info/dependency_links.txt
css2json.egg-info/top_level.txt